clipmac/__init__.py
clipmac/chrisdlg.py
clipmac/chrispane.py
clipmac/chrissql.py
clipmac/chriswin.py
clipmac/config.py
clipmac/icon.png
clipmac-1.0.0.data/scripts/clipmacro.py
clipmac-1.0.0.dist-info/METADATA
clipmac-1.0.0.dist-info/WHEEL
clipmac-1.0.0.dist-info/entry_points.txt
clipmac-1.0.0.dist-info/top_level.txt
clipmac-1.0.0.dist-info/RECORD
