Metadata-Version: 2.4
Name: clipmac
Version: 1.0.0
Summary:  clipmac is clipbard copy / paste tool 
Home-page: https://github.com/pglen/clipmac
Author: Peter Glen
Author-email: peterglen99@gmail.com
Classifier: Programming Language :: Python :: 3
Classifier: License :: OSI Approved :: MIT License
Classifier: Operating System :: OS Independent
Requires-Python: >=3
Requires-Dist: pyvguicom
Dynamic: author
Dynamic: author-email
Dynamic: classifier
Dynamic: description
Dynamic: description-content-type
Dynamic: home-page
Dynamic: requires-dist
Dynamic: requires-python
Dynamic: summary
